__init__.py
ecs_bash.py
__init__.py
db-connect.sh
db-decrypt.js
f_excel_tools-4.3.10.dist-info/METADATA
f_excel_tools-4.3.10.dist-info/WHEEL
f_excel_tools-4.3.10.dist-info/entry_points.txt
f_excel_tools-4.3.10.dist-info/RECORD
