Metadata-Version: 2.3
Name: f-excel-tools
Version: 4.3.10
Summary: AWS tools including ECS bash execution
Author: Filipe Ferreira
Author-email: ola@filipeandre.com
Requires-Python: >=3.12,<4.0
Classifier: Programming Language :: Python :: 3
Classifier: Programming Language :: Python :: 3.12
Classifier: Programming Language :: Python :: 3.13
Requires-Dist: boto3 (>=1.37.13,<2.0.0)
Requires-Dist: inquirer (>=3.4.0,<4.0.0)
Project-URL: Homepage, https://github.com/filipeandre/f-tools
